sysstat_applet-1.1.1.data/data/share/applications/sysstat-applet.desktop
sysstat_applet-1.1.1.data/scripts/sysstat-applet
sysstatapplet/__init__.py
sysstatapplet/cpu.py
sysstatapplet/disk.py
sysstatapplet/mem.py
sysstatapplet/sysstat.py
sysstatapplet/util.py
sysstat_applet-1.1.1.dist-info/LICENSE
sysstat_applet-1.1.1.dist-info/METADATA
sysstat_applet-1.1.1.dist-info/WHEEL
sysstat_applet-1.1.1.dist-info/top_level.txt
sysstat_applet-1.1.1.dist-info/RECORD
