Metadata-Version: 2.1
Name: sysstat-applet
Version: 1.1.1
Summary: Tray applet for system monitoring
Home-page: https://github.com/jmechnich/sysstat-applet
Author: Joerg Mechnich
Author-email: joerg.mechnich@gmail.com
License: GNU GPLv3
Classifier: Programming Language :: Python :: 3
Classifier: License :: OSI Approved :: GNU General Public License v3 (GPLv3)
Classifier: Operating System :: POSIX :: Linux
Classifier: Environment :: X11 Applications :: Qt
Requires-Python: >=3.6
License-File: LICENSE
Requires-Dist: appletlib >=1.1
